<?xml version="1.0" standalone="no"?>

<faction>
	<starting-resources>
		<resource name="gold" amount="500"/>
		<resource name="wood" amount="500"/>
		<resource name="stone" amount="500"/>
		<resource name="oil" amount="60"/>
	</starting-resources>
	<starting-units>
		<unit name="oil" amount="2"/>
		<unit name="headquarters" amount="1"/>
		<unit name="outpost_i" amount="1"/>
		<unit name="recruit" amount="3"/>
		<unit name="rifleman" amount="2"/>
		<unit name="howitzer" amount="1"/>
		<unit name="rocket_launcher" amount="1"/>
		<unit name="gun_trap" amount="0"/>
		<unit name="nuclear_missile_launcher" amount="0"/>
		<unit name="sleeping_gas_soldier" amount="0"/>
		<unit name="uragan_vehicle" amount="0"/>
		<unit name="leclerc_tank" amount="0"/>
		<unit name="conqueror_tank" amount="0"/>
		<unit name="boeing_bomber" amount="0"/>
		<unit name="military_ambulance" amount="0"/>
	</starting-units>
	<music value="true" path="music/the_shining_city.ogg"/>
</faction>


